Workbook

Sheet SB1
A1: Codigo | B1: Descripcion | C1: TS Estandar
A2: 000001 | B2: MERCADERIA SALDOS | C2: 503
A3: 000002 | B3: CINTA PELIGRO X 100 MTS DOBLE FAZ(CP100) | C3: 503
A4: 000003 | B4: CINTA PELIGRO X 200 MTS DOBLE FAZ(CP200) | C4: 503
A5: 000004 | B5: PISTOLA APLICADORA SKELETOR REFORZADA | C5: 503
A6: 000005 | B6: PORTA PINCEL MAGNETICO | C6: 503
A7: 000006 | B7: COBERTURA PLASTICA MULTIUSO 3X3MTS.(AC315) | C7: 503
A8: 000007 | B8: COBERTURA PLASTICA MULTIUSO 3X4MTS.(AC316) | C8: 503
A9: 000008 | B9: COBERTURA PLASTICA MULTIUSO 3X5MTS.(AC317) | C9: 503
A10: 000009 | B10: FONDO ANTIOXIDO COLORIN ROJO X 0,250 | C10: 503
A11: 000010 | B11: ESMALTE SINTETICO TERSUAVE 2EN1 MATE NEGRO X 0,500 | C11: 503
A12: 000011 | B12: ESMALTE SINTETICO TERSUAVE 2EN1 MATE NEGRO X 1 | C12: 503
... A7103: 999998 | B7103: GENERICO 10 LITROS ESTANDAR | C7103: 503
A7104: A00010 | B7104: BIEN DE USO - VEHICULOS
A7105: A00011 | B7105: BIENES DE USO - EQUIPOS COMPUTACION
A7106: A00012 | B7106: BIENES DE USO - MUEBLES Y UTILES
A7107: A00100 | B7107: INGRESOS BRUTOS
A7108: A00101 | B7108: DREI
A7109: A00102 | B7109: IMPUESTO A LAS GANANCIAS
A7110: A00103 | B7110: IMPUESTO BIENES PERSONALES
A7111: A00104 | B7111: ANTICIPO IMPUESTO A LAS GANANCIAS
A7112: A00105 | B7112: ANTICIPO BIENES PERSONALES
A7113: A00106 | B7113: AUTONOMO
A7114: A00107 | B7114: APORTES Y LEYES SOCIALES
A7115: A00108 | B7115: INGRESOS BRUTOS RETENIDOS
... A7128: A00208 | B7128: SEGUROS
A7129: A00300 | B7129: FLETES PROVEEDORES PINTURAS Y ACCESORIOS | C7129: 506
A7130: A00301 | B7130: FLETES PROVEEDORES OTROS SERVICIOS | C7130: 506
A7131: A00303 | B7131: FLETES INTERNOS | C7131: 506
A7132: A00304 | B7132: FLETES A CLIENTES | C7132: 506
A7133: A00305 | B7133: ALQUILERES | C7133: 728
A7134: A00306 | B7134: COMBUSTIBLES
A7135: A00307 | B7135: VARIOS LIBRERIA
A7136: A00308 | B7136: SERVICIO MECANICO | C7136: 504
A7137: A00309 | B7137: GASTOS VARIOS DE MANTENIMIENTO
A7138: A00310 | B7138: COMISIONES Y RENOVACIONES CONTRATOS
A7139: A00311 | B7139: VIATICOS
A7140: A00312 | B7140: MARKETING
A7141: A00313 | B7141: HONORARIOS PROFESIONALES
A7142: A00314 | B7142: VARIOS ELECTRICIDAD | C7142: 708
A7143: A00315 | B7143: VARIOS CONSTRUCCION
A7144: A00316 | B7144: TASA MUNICIPAL
A7145: A00317 | B7145: IMPUESTO INMOBILIARIO
A7146: A00318 | B7146: LUZ, AGUA Y GAS
A7147: A00319 | B7147: TELEFONIA, INTERNET Y COMUNICACION | C7147: 708
A7148: A00320 | B7148: CHEQUE RECHAZADO | C7148: 605
A7149: A00321 | B7149: GASTOS POR CHEQUE RECHAZADO | C7149: 506
A7150: A00322 | B7150: DESCUENTOS FINANCIEROS | C7150: 753
A7151: A00323 | B7151: PATENTES
A7152: A00324 | B7152: IVA
A7153: A00325 | B7153: SERVICIO PICKIT | C7153: 506
A7154: A00326 | B7154: ROPA DE TRABAJO
A7155: A00327 | B7155: DEUDOR INCOBRABLE | C7155: 506
A7156: A00328 | B7156: EVENTO EMPRESARIAL ANUAL / USO GERENCIA
A7157: A00329 | B7157: CREDITO BANCARIO
A7158: A00330 | B7158: INTERESES DEVENGADOS
A7159: A00331 | B7159: ACCION COMPARTIDA GERENCIA
A7160: A00332 | B7160: HONORARIOS Y MANO DE OBRA ALBERDI 1539
A7161: A00333 | B7161: MATERIALES DE CONSTRUCCION VARIOS ALBERDI 1539
A7162: A00334 | B7162: MOBILIARIO Y EQUIPAMIENTOS ALBERDI 1539
A7163: A00335 | B7163: CARGA IVA
A7164: A00336 | B7164: SOPORTE SISTEMA INFORMATICO
A7165: A00337 | B7165: NCC AUTOMATICA PAGO ELECTRÓNICO | C7165: 753
A7166: A00338 | B7166: SELLADO PROVINCIAL
A7167: A00339 | B7167: PREMIOS
A7168: A00340 | B7168: GASTOS PARTICULARES
A7169: M00002 | B7169: TARJETA PLATINO | C7169: 506
A7170: M00003 | B7170: TARJETA BLACK | C7170: 506
A7171: M00004 | B7171: DESCUENTO TARJETA PLATINO | C7171: 506
A7172: M00005 | B7172: DESCUENTO TARJETA BLACK | C7172: 506
A7173: M00006 | B7173: CETOL+LIJA-LIQ | C7173: 506
A7174: M00007 | B7174: CETOL+REMOV | C7174: 506
A7175: M00008 | B7175: ENDUIDO+ESPAT | C7175: 506
A7176: M00009 | B7176: ALBALUX-BAL+PINCEL | C7176: 506
A7177: M00010 | B7177: ALBACRYL+RODILLO | C7177: 506
A7178: M00011 | B7178: PUBLICIDAD GRAFICA, RADIAL Y MEDIOS
A7179: M00012 | B7179: REGALOS EMPRESARIALES
A7180: M00013 | B7180: MERCHANDISING
A7181: M00014 | B7181: EVENTO EMPRESARIAL DE AREA
A7182: M00015 | B7182: ACCION COMPARTIDA MARKETING
A7183: M00016 | B7183: VIATICOS MARKETING
A7184: M00017 | B7184: MATERIAL PROMOCIONAL SUCURSALES / CLIENTES
A7185: M00018 | B7185: SUELDOS / SAC MARKETING
A7186: M00019 | B7186: COMISIONES MARKETING
A7187: M00020 | B7187: APORTES Y LEYES SOCIALES MARKETING
A7188: M00021 | B7188: APORTES SINDICATOS MARKETING
A7189: M00022 | B7189: FAECYS MARKETING
... A7191: M00024 | B7191: SEGURO LA ESTRELLA MARKETING
A7192: P00003 | B7192: ENVASADO | C7192: 503
A7193: P00100 | B7193: MERCADERIA NO CODIFICADA | C7193: 506
A7194: P00101 | B7194: FLETES PROVEEDORES PINTURAS Y ACCESORIOS | C7194: 506
A7195: P00102 | B7195: DESCUENTOS FINANCIEROS | C7195: 753
A7196: P00103 | B7196: REDONDEO 21% | C7196: 503
A7197: P00104 | B7197: DEBITOS FINANCIEROS | C7197: 753
A7198: P00105 | B7198: ACCION COMPARTIDA MARKETING - PROVEEDORES | C7198: 753
A7199: P00106 | B7199: ACCION COMPARTIDA COMERCIAL - PROVEEDORES | C7199: 753
A7200: RH0001 | B7200: ROPA DE TRABAJO
A7201: RH0002 | B7201: REGALOS LABORALES
A7202: RH0003 | B7202: CAPACITACIONES LABORALES
A7203: RH0004 | B7203: ACCION COMPARTIDA RRHH
...

Sheet 001
A1: Cod. Tabla | B1: Cod.Producto | C1: Descripcion | D1: Grupo | E1: Precio Venta | F1: TES | G1: % | H1: Final | I1: Moneda
A2: 001 | B2: 000002 | C2: =IFERROR(VLOOKUP(B2,'SB1'!$A$2:$B$999999,2,FALSE),"") -> CINTA PELIGRO X 100 MTS DOBLE FAZ(CP100) | D2: 0165 | E2: =IFERROR(VLOOKUP(B2,'DA1'!$B$2:$D$999999,3,FALSE),"") | F2: =IFERROR(VLOOKUP(B2,'SB1'!$A$2:$C$999999,3,FALSE),"") -> 503 | G2: =E2*1.04 -> #VALUE! | H2: =G2*1.21 -> #VALUE! | I2: 1
A3: 001 | B3: 000003 | C3: =IFERROR(VLOOKUP(B3,'SB1'!$A$2:$B$999999,2,FALSE),"") -> CINTA PELIGRO X 200 MTS DOBLE FAZ(CP200) | D3: 0165 | E3: =IFERROR(VLOOKUP(B3,'DA1'!$B$2:$D$999999,3,FALSE),"") | F3: =IFERROR(VLOOKUP(B3,'SB1'!$A$2:$C$999999,3,FALSE),"") -> 503 | G3: =E3*1.04 -> #VALUE! | H3: =G3*1.21 -> #VALUE! | I3: 1
A4: 001 | B4: 000004 | C4: =IFERROR(VLOOKUP(B4,'SB1'!$A$2:$B$999999,2,FALSE),"") -> PISTOLA APLICADORA SKELETOR REFORZADA | D4: 0165 | E4: =IFERROR(VLOOKUP(B4,'DA1'!$B$2:$D$999999,3,FALSE),"") | F4: =IFERROR(VLOOKUP(B4,'SB1'!$A$2:$C$999999,3,FALSE),"") -> 503 | G4: =E4*1.04 -> #VALUE! | H4: =G4*1.21 -> #VALUE! | I4: 1
A5: 001 | B5: 000005 | C5: =IFERROR(VLOOKUP(B5,'SB1'!$A$2:$B$999999,2,FALSE),"") -> PORTA PINCEL MAGNETICO | D5: 0165 | E5: =IFERROR(VLOOKUP(B5,'DA1'!$B$2:$D$999999,3,FALSE),"") | F5: =IFERROR(VLOOKUP(B5,'SB1'!$A$2:$C$999999,3,FALSE),"") -> 503 | G5: =E5*1.04 -> #VALUE! | H5: =G5*1.21 -> #VALUE! | I5: 1
A6: 001 | B6: 000006 | C6: =IFERROR(VLOOKUP(B6,'SB1'!$A$2:$B$999999,2,FALSE),"") -> COBERTURA PLASTICA MULTIUSO 3X3MTS.(AC315) | D6: 0165 | E6: =IFERROR(VLOOKUP(B6,'DA1'!$B$2:$D$999999,3,FALSE),"") | F6: =IFERROR(VLOOKUP(B6,'SB1'!$A$2:$C$999999,3,FALSE),"") -> 503 | G6: =E6*1.04 -> #VALUE! | H6: =G6*1.21 -> #VALUE! | I6: 1
A7: 001 | B7: 000007 | C7: =IFERROR(VLOOKUP(B7,'SB1'!$A$2:$B$999999,2,FALSE),"") -> COBERTURA PLASTICA MULTIUSO 3X4MTS.(AC316) | D7: 0165 | E7: =IFERROR(VLOOKUP(B7,'DA1'!$B$2:$D$999999,3,FALSE),"") | F7: =IFERROR(VLOOKUP(B7,'SB1'!$A$2:$C$999999,3,FALSE),"") -> 503 | G7: =E7*1.04 -> #VALUE! | H7: =G7*1.21 -> #VALUE! | I7: 1
A8: 001 | B8: 000008 | C8: =IFERROR(VLOOKUP(B8,'SB1'!$A$2:$B$999999,2,FALSE),"") -> COBERTURA PLASTICA MULTIUSO 3X5MTS.(AC317) | D8: 0165 | E8: =IFERROR(VLOOKUP(B8,'DA1'!$B$2:$D$999999,3,FALSE),"") | F8: =IFERROR(VLOOKUP(B8,'SB1'!$A$2:$C$999999,3,FALSE),"") -> 503 | G8: =E8*1.04 -> #VALUE! | H8: =G8*1.21 -> #VALUE! | I8: 1
A9: 001 | B9: 000010 | C9: =IFERROR(VLOOKUP(B9,'SB1'!$A$2:$B$999999,2,FALSE),"") -> ESMALTE SINTETICO TERSUAVE 2EN1 MATE NEGRO X 0,500 | D9: 0152 | E9: =IFERROR(VLOOKUP(B9,'DA1'!$B$2:$D$999999,3,FALSE),"") | F9: =IFERROR(VLOOKUP(B9,'SB1'!$A$2:$C$999999,3,FALSE),"") -> 503 | G9: =E9*1.04 -> #VALUE! | H9: =G9*1.21 -> #VALUE! | I9: 1
A10: 001 | B10: 000011 | C10: =IFERROR(VLOOKUP(B10,'SB1'!$A$2:$B$999999,2,FALSE),"") -> ESMALTE SINTETICO TERSUAVE 2EN1 MATE NEGRO X 1 | D10: 0152 | E10: =IFERROR(VLOOKUP(B10,'DA1'!$B$2:$D$999999,3,FALSE),"") | F10: =IFERROR(VLOOKUP(B10,'SB1'!$A$2:$C$999999,3,FALSE),"") -> 503 | G10: =E10*1.04 -> #VALUE! | H10: =G10*1.21 -> #VALUE! | I10: 1
A11: 001 | B11: 000012 | C11: =IFERROR(VLOOKUP(B11,'SB1'!$A$2:$B$999999,2,FALSE),"") -> ESMALTE SINTETICO TERSUAVE 2EN1 MATE NEGRO X 4 | D11: 0152 | E11: =IFERROR(VLOOKUP(B11,'DA1'!$B$2:$D$999999,3,FALSE),"") | F11: =IFERROR(VLOOKUP(B11,'SB1'!$A$2:$C$999999,3,FALSE),"") -> 503 | G11: =E11*1.04 -> #VALUE! | H11: =G11*1.21 -> #VALUE! | I11: 1
A12: 001 | B12: 000013 | C12: =IFERROR(VLOOKUP(B12,'SB1'!$A$2:$B$999999,2,FALSE),"") -> ESMALTE SINTETICO TERSUAVE 2EN1 MATE BLANCO X 0,500 | D12: 0152 | E12: =IFERROR(VLOOKUP(B12,'DA1'!$B$2:$D$999999,3,FALSE),"") | F12: =IFERROR(VLOOKUP(B12,'SB1'!$A$2:$C$999999,3,FALSE),"") -> 503 | G12: =E12*1.04 -> #VALUE! | H12: =G12*1.21 -> #VALUE! | I12: 1
A13: 001 | B13: 000014 | C13: =IFERROR(VLOOKUP(B13,'SB1'!$A$2:$B$999999,2,FALSE),"") -> ESMALTE SINTETICO TERSUAVE 2EN1 MATE BLANCO X 1 | D13: 0152 | E13: =IFERROR(VLOOKUP(B13,'DA1'!$B$2:$D$999999,3,FALSE),"") | F13: =IFERROR(VLOOKUP(B13,'SB1'!$A$2:$C$999999,3,FALSE),"") -> 503 | G13: =E13*1.04 -> #VALUE! | H13: =G13*1.21 -> #VALUE! | I13: 1
... A16: 001 | B16: 000025 | C16: =IFERROR(VLOOKUP(B16,'SB1'!$A$2:$B$999999,2,FALSE),"") -> AUTOPOLISH COLORIN BICAPA X 0,450 | D16: 0166 | E16: =IFERROR(VLOOKUP(B16,'DA1'!$B$2:$D$999999,3,FALSE),"") | F16: =IFERROR(VLOOKUP(B16,'SB1'!$A$2:$C$999999,3,FALSE),"") -> 503 | G16: =E16*1.04 -> #VALUE! | H16: =G16*1.21 -> #VALUE! | I16: 1
A17: 001 | B17: 000026 | C17: =IFERROR(VLOOKUP(B17,'SB1'!$A$2:$B$999999,2,FALSE),"") -> BARNIZ PARA MADERA EXTERIOR ALBATROS AL AGUA BRILLANTE INCOLORO X 1 | D17: 0902 | E17: =IFERROR(VLOOKUP(B17,'DA1'!$B$2:$D$999999,3,FALSE),"") | F17: =IFERROR(VLOOKUP(B17,'SB1'!$A$2:$C$999999,3,FALSE),"") -> 503 | G17: =E17*1.04 -> #VALUE! | H17: =G17*1.21 -> #VALUE!
A18: 001 | B18: 000027 | C18: =IFERROR(VLOOKUP(B18,'SB1'!$A$2:$B$999999,2,FALSE),"") -> BARNIZ PARA MADERA EXTERIOR ALBATROS AL AGUA BRILLANTE INCOLORO X 4 | D18: 0902 | E18: =IFERROR(VLOOKUP(B18,'DA1'!$B$2:$D$999999,3,FALSE),"") | F18: =IFERROR(VLOOKUP(B18,'SB1'!$A$2:$C$999999,3,FALSE),"") -> 503 | G18: =E18*1.04 -> #VALUE! | H18: =G18*1.21 -> #VALUE! | I18: 1
A19: 001 | B19: 000028 | C19: =IFERROR(VLOOKUP(B19,'SB1'!$A$2:$B$999999,2,FALSE),"") -> REMOVEDOR GEL PETRILAC X 4 | D19: 0902 | E19: =IFERROR(VLOOKUP(B19,'DA1'!$B$2:$D$999999,3,FALSE),"") | F19: =IFERROR(VLOOKUP(B19,'SB1'!$A$2:$C$999999,3,FALSE),"") -> 503 | G19: =E19*1.04 -> #VALUE! | H19: =G19*1.21 -> #VALUE!
A20: 001 | B20: 000034 | C20: =IFERROR(VLOOKUP(B20,'SB1'!$A$2:$B$999999,2,FALSE),"") -> LATEX PARA CIELORRASOS COLORIN MATE BLANCO X 20 | D20: 0116 | E20: =IFERROR(VLOOKUP(B20,'DA1'!$B$2:$D$999999,3,FALSE),"") | F20: =IFERROR(VLOOKUP(B20,'SB1'!$A$2:$C$999999,3,FALSE),"") -> 503 | G20: =E20*1.04 -> #VALUE! | H20: =G20*1.21 -> #VALUE! | I20: 1
A21: 001 | B21: 000041 | C21: =IFERROR(VLOOKUP(B21,'SB1'!$A$2:$B$999999,2,FALSE),"") -> BARNIZ PARA MADERA INTERIOR CRISTALBA PU MATE NATURAL X 1 | D21: 0107 | E21: =IFERROR(VLOOKUP(B21,'DA1'!$B$2:$D$999999,3,FALSE),"") | F21: =IFERROR(VLOOKUP(B21,'SB1'!$A$2:$C$999999,3,FALSE),"") -> 503 | G21: =E21*1.04 -> #VALUE! | H21: =G21*1.21 -> #VALUE! | I21: 1
A22: 001 | B22: 000042 | C22: =IFERROR(VLOOKUP(B22,'SB1'!$A$2:$B$999999,2,FALSE),"") -> BARNIZ PARA MADERA INTERIOR CRISTALBA PU MATE NATURAL X 4 | D22: 0107 | E22: =IFERROR(VLOOKUP(B22,'DA1'!$B$2:$D$999999,3,FALSE),"") | F22: =IFERROR(VLOOKUP(B22,'SB1'!$A$2:$C$999999,3,FALSE),"") -> 503 | G22: =E22*1.04 -> #VALUE! | H22: =G22*1.21 -> #VALUE! | I22: 1
A23: 001 | B23: 000043 | C23: =IFERROR(VLOOKUP(B23,'SB1'!$A$2:$B$999999,2,FALSE),"") -> MEZCLADOR PROFESIONAL(MIXER) Ø8CMX40CM | D23: 0165 | E23: =IFERROR(VLOOKUP(B23,'DA1'!$B$2:$D$999999,3,FALSE),"") | F23: =IFERROR(VLOOKUP(B23,'SB1'!$A$2:$C$999999,3,FALSE),"") -> 503 | G23: =E23*1.04 -> #VALUE! | H23: =G23*1.21 -> #VALUE! | I23: 1
A24: 001 | B24: 000044 | C24: =IFERROR(VLOOKUP(B24,'SB1'!$A$2:$B$999999,2,FALSE),"") -> PALETA ABRELATA 30CM | D24: 0165 | E24: =IFERROR(VLOOKUP(B24,'DA1'!$B$2:$D$999999,3,FALSE),"") | F24: =IFERROR(VLOOKUP(B24,'SB1'!$A$2:$C$999999,3,FALSE),"") -> 503 | G24: =E24*1.04 -> #VALUE! | H24: =G24*1.21 -> #VALUE! | I24: 1
A25: 001 | B25: 000046 | C25: =IFERROR(VLOOKUP(B25,'SB1'!$A$2:$B$999999,2,FALSE),"") -> JUEGO DE LAMINAS DE MASILLAR (5-8-10-12) | D25: 0165 | E25: =IFERROR(VLOOKUP(B25,'DA1'!$B$2:$D$999999,3,FALSE),"") | F25: =IFERROR(VLOOKUP(B25,'SB1'!$A$2:$C$999999,3,FALSE),"") -> 503 | G25: =E25*1.04 -> #VALUE! | H25: =G25*1.21 -> #VALUE! | I25: 1
A26: 001 | B26: 000050 | C26: =IFERROR(VLOOKUP(B26,'SB1'!$A$2:$B$999999,2,FALSE),"") -> TRINCHETA-CUTTER PRO GUIA METAL USO PESADO | D26: 0165 | E26: =IFERROR(VLOOKUP(B26,'DA1'!$B$2:$D$999999,3,FALSE),"") | F26: =IFERROR(VLOOKUP(B26,'SB1'!$A$2:$C$999999,3,FALSE),"") -> 503 | G26: =E26*1.04 -> #VALUE! | H26: =G26*1.21 -> #VALUE! | I26: 1
A27: 001 | B27: 000051 | C27: =IFERROR(VLOOKUP(B27,'SB1'!$A$2:$B$999999,2,FALSE),"") -> GUANTE NITRILO SOFT NEGRO S/P #XL MEDIGLOVE X 100 | D27: 0177 | E27: =IFERROR(VLOOKUP(B27,'DA1'!$B$2:$D$999999,3,FALSE),"") | F27: =IFERROR(VLOOKUP(B27,'SB1'!$A$2:$C$999999,3,FALSE),"") -> 503 | G27: =E27*1.04 -> #VALUE! | H27: =G27*1.21 -> #VALUE! | I27: 1
A28: 001 | B28: 000052 | C28: =IFERROR(VLOOKUP(B28,'SB1'!$A$2:$B$999999,2,FALSE),"") -> BALDE PLASTICO REFORZADO 8LTS. (BC01) | D28: 0176 | E28: =IFERROR(VLOOKUP(B28,'DA1'!$B$2:$D$999999,3,FALSE),"") | F28: =IFERROR(VLOOKUP(B28,'SB1'!$A$2:$C$999999,3,FALSE),"") -> 503 | G28: =E28*1.04 -> #VALUE! | H28: =G28*1.21 -> #VALUE! | I28: 1
A29: 001 | B29: 000054 | C29: =IFERROR(VLOOKUP(B29,'SB1'!$A$2:$B$999999,2,FALSE),"") -> BASE ACRILICA-UNIVERSAL MMB X 0,875 | D29: 0137 | E29: =IFERROR(VLOOKUP(B29,'DA1'!$B$2:$D$999999,3,FALSE),"") | F29: =IFERROR(VLOOKUP(B29,'SB1'!$A$2:$C$999999,3,FALSE),"") -> 503 | G29: =E29*1.04 -> #VALUE! | H29: =G29*1.21 -> #VALUE! | I29: 1
A30: 001 | B30: 000055 | C30: =IFERROR(VLOOKUP(B30,'SB1'!$A$2:$B$999999,2,FALSE),"") -> BASE ACRILICA-UNIVERSAL MMB X 3,500 | D30: 0137 | E30: =IFERROR(VLOOKUP(B30,'DA1'!$B$2:$D$999999,3,FALSE),"") | F30: =IFERROR(VLOOKUP(B30,'SB1'!$A$2:$C$999999,3,FALSE),"") -> 503 | G30: =E30*1.04 -> #VALUE! | H30: =G30*1.21 -> #VALUE! | I30: 1
A31: 001 | B31: 000057 | C31: =IFERROR(VLOOKUP(B31,'SB1'!$A$2:$B$999999,2,FALSE),"") -> FONDO ANTIOXIDO UNIVERSAL MMB X 1 | D31: 0137 | E31: =IFERROR(VLOOKUP(B31,'DA1'!$B$2:$D$999999,3,FALSE),"") | F31: =IFERROR(VLOOKUP(B31,'SB1'!$A$2:$C$999999,3,FALSE),"") -> 503 | G31: =E31*1.04 -> #VALUE! | H31: =G31*1.21 -> #VALUE! | I31: 1
... A33: 001 | B33: 000059 | C33: =IFERROR(VLOOKUP(B33,'SB1'!$A$2:$B$999999,2,FALSE),"") -> MASILLA UNIVERSAL MMB X 1 | D33: 0137 | E33: =IFERROR(VLOOKUP(B33,'DA1'!$B$2:$D$999999,3,FALSE),"") | F33: =IFERROR(VLOOKUP(B33,'SB1'!$A$2:$C$999999,3,FALSE),"") -> 503 | G33: =E33*1.04 -> #VALUE! | H33: =G33*1.21 -> #VALUE! | I33: 1
A34: 001 | B34: 000060 | C34: =IFERROR(VLOOKUP(B34,'SB1'!$A$2:$B$999999,2,FALSE),"") -> MASILLA UNIVERSAL MMB X 4 | D34: 0902 | E34: =IFERROR(VLOOKUP(B34,'DA1'!$B$2:$D$999999,3,FALSE),"") | F34: =IFERROR(VLOOKUP(B34,'SB1'!$A$2:$C$999999,3,FALSE),"") -> 503 | G34: =E34*1.04 -> #VALUE! | H34: =G34*1.21 -> #VALUE!
A35: 001 | B35: 000065 | C35: =IFERROR(VLOOKUP(B35,'SB1'!$A$2:$B$999999,2,FALSE),"") -> LATEX EXTERIOR COLORIN TITANIO PRO BLANCO X 10 | D35: 0116 | E35: =IFERROR(VLOOKUP(B35,'DA1'!$B$2:$D$999999,3,FALSE),"") | F35: =IFERROR(VLOOKUP(B35,'SB1'!$A$2:$C$999999,3,FALSE),"") -> 503 | G35: =E35*1.04 -> #VALUE! | H35: =G35*1.21 -> #VALUE! | I35: 1
A36: 001 | B36: 000067 | C36: =IFERROR(VLOOKUP(B36,'SB1'!$A$2:$B$999999,2,FALSE),"") -> PROTECTOR PARA MADERA CETOL BELLEZA NATURAL MATE INCOLORO X 1 | D36: 0105 | E36: =IFERROR(VLOOKUP(B36,'DA1'!$B$2:$D$999999,3,FALSE),"") | F36: =IFERROR(VLOOKUP(B36,'SB1'!$A$2:$C$999999,3,FALSE),"") -> 503 | G36: =E36*1.04 -> #VALUE! | H36: =G36*1.21 -> #VALUE! | I36: 1
A37: 001 | B37: 000068 | C37: =IFERROR(VLOOKUP(B37,'SB1'!$A$2:$B$999999,2,FALSE),"") -> PROTECTOR PARA MADERA CETOL BELLEZA NATURAL MATE INCOLORO X 4 | D37: 0105 | E37: =IFERROR(VLOOKUP(B37,'DA1'!$B$2:$D$999999,3,FALSE),"") | F37: =IFERROR(VLOOKUP(B37,'SB1'!$A$2:$C$999999,3,FALSE),"") -> 503 | G37: =E37*1.04 -> #VALUE! | H37: =G37*1.21 -> #VALUE! | I37: 1
A38: 001 | B38: 000071 | C38: =IFERROR(VLOOKUP(B38,'SB1'!$A$2:$B$999999,2,FALSE),"") -> CUCHARA WELBY N 7 (CU02) | D38: 0176 | E38: =IFERROR(VLOOKUP(B38,'DA1'!$B$2:$D$999999,3,FALSE),"") | F38: =IFERROR(VLOOKUP(B38,'SB1'!$A$2:$C$999999,3,FALSE),"") -> 503 | G38: =E38*1.04 -> #VALUE! | H38: =G38*1.21 -> #VALUE! | I38: 1
A39: 001 | B39: 000072 | C39: =IFERROR(VLOOKUP(B39,'SB1'!$A$2:$B$999999,2,FALSE),"") -> ESMALTE SINTETICO TERSUAVE 2EN1 MATE NEGRO X 20 | D39: 0152 | E39: =IFERROR(VLOOKUP(B39,'DA1'!$B$2:$D$999999,3,FALSE),"") | F39: =IFERROR(VLOOKUP(B39,'SB1'!$A$2:$C$999999,3,FALSE),"") -> 503 | G39: =E39*1.04 -> #VALUE! | H39: =G39*1.21 -> #VALUE! | I39: 1
A40: 001 | B40: 000073 | C40: =IFERROR(VLOOKUP(B40,'SB1'!$A$2:$B$999999,2,FALSE),"") -> D8501 PRIMER 2K DP4000 BLANCO AUTONIVELANTE (G1) X 1 | D40: 0134 | E40: =IFERROR(VLOOKUP(B40,'DA1'!$B$2:$D$999999,3,FALSE),"") | F40: =IFERROR(VLOOKUP(B40,'SB1'!$A$2:$C$999999,3,FALSE),"") -> 503 | G40: =E40*1.04 -> #VALUE! | H40: =G40*1.21 -> #VALUE! | I40: 3
A41: 001 | B41: 000074 | C41: =IFERROR(VLOOKUP(B41,'SB1'!$A$2:$B$999999,2,FALSE),"") -> D8507 PRIMER 2K DP4000 GRIS AUTONIVELANTE (G7) X 1 | D41: 0134 | E41: =IFERROR(VLOOKUP(B41,'DA1'!$B$2:$D$999999,3,FALSE),"") | F41: =IFERROR(VLOOKUP(B41,'SB1'!$A$2:$C$999999,3,FALSE),"") -> 503 | G41: =E41*1.04 -> #VALUE! | H41: =G41*1.21 -> #VALUE! | I41: 3
A42: 001 | B42: 000075 | C42: =IFERROR(VLOOKUP(B42,'SB1'!$A$2:$B$999999,2,FALSE),"") -> D8238 CATALIZADOR P/ D8115 / D8117 / D8501/D8507 (DP4000) X 0,500 "DISCONTINUADO" | D42: 0902 | E42: =IFERROR(VLOOKUP(B42,'DA1'!$B$2:$D$999999,3,FALSE),"") | F42: =IFERROR(VLOOKUP(B42,'SB1'!$A$2:$C$999999,3,FALSE),"") -> 503 | G42: =E42*1.04 -> #VALUE! | H42: =G42*1.21 -> #VALUE!
A43: 001 | B43: 000078 | C43: =IFERROR(VLOOKUP(B43,'SB1'!$A$2:$B$999999,2,FALSE),"") -> LATEX PARA CIELORRASOS COLORIN MATE BLANCO X 10 | D43: 0116 | E43: =IFERROR(VLOOKUP(B43,'DA1'!$B$2:$D$999999,3,FALSE),"") | F43: =IFERROR(VLOOKUP(B43,'SB1'!$A$2:$C$999999,3,FALSE),"") -> 503 | G43: =E43*1.04 -> #VALUE! | H43: =G43*1.21 -> #VALUE! | I43: 1
A44: 001 | B44: 000082 | C44: =IFERROR(VLOOKUP(B44,'SB1'!$A$2:$B$999999,2,FALSE),"") -> ENDUIDO INTERIOR COLORIN SUPER LIVIANO X 20 | D44: 0116 | E44: =IFERROR(VLOOKUP(B44,'DA1'!$B$2:$D$999999,3,FALSE),"") | F44: =IFERROR(VLOOKUP(B44,'SB1'!$A$2:$C$999999,3,FALSE),"") -> 503 | G44: =E44*1.04 -> #VALUE! | H44: =G44*1.21 -> #VALUE! | I44: 1
A45: 001 | B45: 000083 | C45: =IFERROR(VLOOKUP(B45,'SB1'!$A$2:$B$999999,2,FALSE),"") -> PROTECTOR SUBCARROCERIA MMB ACUOSA NEGRO X 1 | D45: 0137 | E45: =IFERROR(VLOOKUP(B45,'DA1'!$B$2:$D$999999,3,FALSE),"") | F45: =IFERROR(VLOOKUP(B45,'SB1'!$A$2:$C$999999,3,FALSE),"") -> 503 | G45: =E45*1.04 -> #VALUE! | H45: =G45*1.21 -> #VALUE! | I45: 1
A46: 001 | B46: 000084 | C46: =IFERROR(VLOOKUP(B46,'SB1'!$A$2:$B$999999,2,FALSE),"") -> PROTECTOR SUBCARROCERIA MMB ACUOSA BLANCO X 1 | D46: 0137 | E46: =IFERROR(VLOOKUP(B46,'DA1'!$B$2:$D$999999,3,FALSE),"") | F46: =IFERROR(VLOOKUP(B46,'SB1'!$A$2:$C$999999,3,FALSE),"") -> 503 | G46: =E46*1.04 -> #VALUE! | H46: =G46*1.21 -> #VALUE! | I46: 1
A47: 001 | B47: 000085 | C47: =IFERROR(VLOOKUP(B47,'SB1'!$A$2:$B$999999,2,FALSE),"") -> MAGIPLAST ANTI-HONGO X 0,200 | D47: 0129 | E47: =IFERROR(VLOOKUP(B47,'DA1'!$B$2:$D$999999,3,FALSE),"") | F47: =IFERROR(VLOOKUP(B47,'SB1'!$A$2:$C$999999,3,FALSE),"") -> 503 | G47: =E47*1.04 -> #VALUE! | H47: =G47*1.21 -> #VALUE! | I47: 1
A48: 001 | B48: 000086 | C48: =IFERROR(VLOOKUP(B48,'SB1'!$A$2:$B$999999,2,FALSE),"") -> PASTA PULIR MMB FINA X 0,500 | D48: 0137 | E48: =IFERROR(VLOOKUP(B48,'DA1'!$B$2:$D$999999,3,FALSE),"") | F48: =IFERROR(VLOOKUP(B48,'SB1'!$A$2:$C$999999,3,FALSE),"") -> 503 | G48: =E48*1.04 -> #VALUE! | H48: =G48*1.21 -> #VALUE! | I48: 1
A49: 001 | B49: 000087 | C49: =IFERROR(VLOOKUP(B49,'SB1'!$A$2:$B$999999,2,FALSE),"") -> AUTOPOLISH COLORIN CLASICO X 0,450 | D49: 0166 | E49: =IFERROR(VLOOKUP(B49,'DA1'!$B$2:$D$999999,3,FALSE),"") | F49: =IFERROR(VLOOKUP(B49,'SB1'!$A$2:$C$999999,3,FALSE),"") -> 503 | G49: =E49*1.04 -> #VALUE! | H49: =G49*1.21 -> #VALUE! | I49: 1
A50: 001 | B50: 000088 | C50: =IFERROR(VLOOKUP(B50,'SB1'!$A$2:$B$999999,2,FALSE),"") -> REMOVEDOR GEL PETRILAC X 1 | D50: 0902 | E50: =IFERROR(VLOOKUP(B50,'DA1'!$B$2:$D$999999,3,FALSE),"") | F50: =IFERROR(VLOOKUP(B50,'SB1'!$A$2:$C$999999,3,FALSE),"") -> 503 | G50: =E50*1.04 -> #VALUE! | H50: =G50*1.21 -> #VALUE!
A51: 001 | B51: 000089 | C51: =IFERROR(VLOOKUP(B51,'SB1'!$A$2:$B$999999,2,FALSE),"") -> ESMALTE SINTETICO TERSUAVE 2EN1 MATE NEGRO X 0,250 | D51: 0152 | E51: =IFERROR(VLOOKUP(B51,'DA1'!$B$2:$D$999999,3,FALSE),"") | F51: =IFERROR(VLOOKUP(B51,'SB1'!$A$2:$C$999999,3,FALSE),"") -> 503 | G51: =E51*1.04 -> #VALUE! | H51: =G51*1.21 -> #VALUE! | I51: 1
A52: 001 | B52: 000097 | C52: =IFERROR(VLOOKUP(B52,'SB1'!$A$2:$B$999999,2,FALSE),"") -> FIJADOR PARA PARED ALBA AL AGUARRAS X 20 | D52: 0107 | E52: =IFERROR(VLOOKUP(B52,'DA1'!$B$2:$D$999999,3,FALSE),"") | F52: =IFERROR(VLOOKUP(B52,'SB1'!$A$2:$C$999999,3,FALSE),"") -> 503 | G52: =E52*1.04 -> #VALUE! | H52: =G52*1.21 -> #VALUE! | I52: 1
A53: 001 | B53: 000098 | C53: =IFERROR(VLOOKUP(B53,'SB1'!$A$2:$B$999999,2,FALSE),"") -> PROTECTOR SUBCARROCERIAS ACUOSA TERSUAVE NEGRO X 1 | D53: 0902 | E53: =IFERROR(VLOOKUP(B53,'DA1'!$B$2:$D$999999,3,FALSE),"") | F53: =IFERROR(VLOOKUP(B53,'SB1'!$A$2:$C$999999,3,FALSE),"") -> 503 | G53: =E53*1.04 -> #VALUE! | H53: =G53*1.21 -> #VALUE!
A54: 001 | B54: 000100 | C54: =IFERROR(VLOOKUP(B54,'SB1'!$A$2:$B$999999,2,FALSE),"") -> IMPERMEABILIZANTE PARA FRENTES Y MUROS ALBAFRENT MATE BLANCO X 10 | D54: 0107 | E54: =IFERROR(VLOOKUP(B54,'DA1'!$B$2:$D$999999,3,FALSE),"") | F54: =IFERROR(VLOOKUP(B54,'SB1'!$A$2:$C$999999,3,FALSE),"") -> 503 | G54: =E54*1.04 -> #VALUE! | H54: =G54*1.21 -> #VALUE! | I54: 1
A55: 001 | B55: 000102 | C55: =IFERROR(VLOOKUP(B55,'SB1'!$A$2:$B$999999,2,FALSE),"") -> PROMOTOR ADHESION PARA PLASTICO MMB X 1 | D55: 0137 | E55: =IFERROR(VLOOKUP(B55,'DA1'!$B$2:$D$999999,3,FALSE),"") | F55: =IFERROR(VLOOKUP(B55,'SB1'!$A$2:$C$999999,3,FALSE),"") -> 503 | G55: =E55*1.04 -> #VALUE! | H55: =G55*1.21 -> #VALUE! | I55: 1
A56: 001 | B56: 000103 | C56: =IFERROR(VLOOKUP(B56,'SB1'!$A$2:$B$999999,2,FALSE),"") -> LLANA DENTADA SANTA JUANA 30 4X4 | D56: 0148 | E56: =IFERROR(VLOOKUP(B56,'DA1'!$B$2:$D$999999,3,FALSE),"") | F56: =IFERROR(VLOOKUP(B56,'SB1'!$A$2:$C$999999,3,FALSE),"") -> 503 | G56: =E56*1.04 -> #VALUE! | H56: =G56*1.21 -> #VALUE! | I56: 1
A57: 001 | B57: 000105 | C57: =IFERROR(VLOOKUP(B57,'SB1'!$A$2:$B$999999,2,FALSE),"") -> ESMALTE PARA AZULEJOS ALBA AL AGUA BRILLANTE X 0,900 | D57: 0107 | E57: =IFERROR(VLOOKUP(B57,'DA1'!$B$2:$D$999999,3,FALSE),"") | F57: =IFERROR(VLOOKUP(B57,'SB1'!$A$2:$C$999999,3,FALSE),"") -> 503 | G57: =E57*1.04 -> #VALUE! | H57: =G57*1.21 -> #VALUE! | I57: 1
A58: 001 | B58: 000106 | C58: =IFERROR(VLOOKUP(B58,'SB1'!$A$2:$B$999999,2,FALSE),"") -> ESMALTE PARA AZULEJOS ALBA AL AGUA BRILLANTE X 3,600 | D58: 0107 | E58: =IFERROR(VLOOKUP(B58,'DA1'!$B$2:$D$999999,3,FALSE),"") | F58: =IFERROR(VLOOKUP(B58,'SB1'!$A$2:$C$999999,3,FALSE),"") -> 503 | G58: =E58*1.04 -> #VALUE! | H58: =G58*1.21 -> #VALUE! | I58: 1
A59: 001 | B59: 000108 | C59: =IFERROR(VLOOKUP(B59,'SB1'!$A$2:$B$999999,2,FALSE),"") -> CUCHARA WELBY CUCHARIN N 5 1/2 (CU08) | D59: 0176 | E59: =IFERROR(VLOOKUP(B59,'DA1'!$B$2:$D$999999,3,FALSE),"") | F59: =IFERROR(VLOOKUP(B59,'SB1'!$A$2:$C$999999,3,FALSE),"") -> 503 | G59: =E59*1.04 -> #VALUE! | H59: =G59*1.21 -> #VALUE! | I59: 1
A60: 001 | B60: 000110 | C60: =IFERROR(VLOOKUP(B60,'SB1'!$A$2:$B$999999,2,FALSE),"") -> LATEX INTERIOR ALBALATEX MATE BLANCO X 1 | D60: 0107 | E60: =IFERROR(VLOOKUP(B60,'DA1'!$B$2:$D$999999,3,FALSE),"") | F60: =IFERROR(VLOOKUP(B60,'SB1'!$A$2:$C$999999,3,FALSE),"") -> 503 | G60: =E60*1.04 -> #VALUE! | H60: =G60*1.21 -> #VALUE! | I60: 1
A61: 001 | B61: 000111 | C61: =IFERROR(VLOOKUP(B61,'SB1'!$A$2:$B$999999,2,FALSE),"") -> LATEX INTERIOR ALBALATEX MATE BLANCO X 4 | D61: 0107 | E61: =IFERROR(VLOOKUP(B61,'DA1'!$B$2:$D$999999,3,FALSE),"") | F61: =IFERROR(VLOOKUP(B61,'SB1'!$A$2:$C$999999,3,FALSE),"") -> 503 | G61: =E61*1.04 -> #VALUE! | H61: =G61*1.21 -> #VALUE! | I61: 1
A62: 001 | B62: 000112 | C62: =IFERROR(VLOOKUP(B62,'SB1'!$A$2:$B$999999,2,FALSE),"") -> FRATACHO PLASTICO 30CM CON GOMA ESPUMA (FR08) | D62: 0176 | E62: =IFERROR(VLOOKUP(B62,'DA1'!$B$2:$D$999999,3,FALSE),"") | F62: =IFERROR(VLOOKUP(B62,'SB1'!$A$2:$C$999999,3,FALSE),"") -> 503 | G62: =E62*1.04 -> #VALUE! | H62: =G62*1.21 -> #VALUE! | I62: 1
A63: 001 | B63: 000113 | C63: =IFERROR(VLOOKUP(B63,'SB1'!$A$2:$B$999999,2,FALSE),"") -> LATEX INTERIOR ALBALATEX MATE BLANCO X 20 | D63: 0107 | E63: =IFERROR(VLOOKUP(B63,'DA1'!$B$2:$D$999999,3,FALSE),"") | F63: =IFERROR(VLOOKUP(B63,'SB1'!$A$2:$C$999999,3,FALSE),"") -> 503 | G63: =E63*1.04 -> #VALUE! | H63: =G63*1.21 -> #VALUE! | I63: 1
A64: 001 | B64: 000114 | C64: =IFERROR(VLOOKUP(B64,'SB1'!$A$2:$B$999999,2,FALSE),"") -> LATEX INTERIOR ALBALATEX DESIGN SATINADO BLANCO X 1 | D64: 0107 | E64: =IFERROR(VLOOKUP(B64,'DA1'!$B$2:$D$999999,3,FALSE),"") | F64: =IFERROR(VLOOKUP(B64,'SB1'!$A$2:$C$999999,3,FALSE),"") -> 503 | G64: =E64*1.04 -> #VALUE! | H64: =G64*1.21 -> #VALUE! | I64: 1
A65: 001 | B65: 000115 | C65: =IFERROR(VLOOKUP(B65,'SB1'!$A$2:$B$999999,2,FALSE),"") -> LATEX INTERIOR ALBALATEX DESIGN SATINADO BLANCO X 4 | D65: 0107 | E65: =IFERROR(VLOOKUP(B65,'DA1'!$B$2:$D$999999,3,FALSE),"") | F65: =IFERROR(VLOOKUP(B65,'SB1'!$A$2:$C$999999,3,FALSE),"") -> 503 | G65: =E65*1.04 -> #VALUE! | H65: =G65*1.21 -> #VALUE! | I65: 1
... A71: 001 | B71: 000121 | C71: =IFERROR(VLOOKUP(B71,'SB1'!$A$2:$B$999999,2,FALSE),"") -> LATEX PARA CIELORRASOS ALBA MATE BLANCO X 20 | D71: 0107 | E71: =IFERROR(VLOOKUP(B71,'DA1'!$B$2:$D$999999,3,FALSE),"") | F71: =IFERROR(VLOOKUP(B71,'SB1'!$A$2:$C$999999,3,FALSE),"") -> 503 | G71: =E71*1.04 -> #VALUE! | H71: =G71*1.21 -> #VALUE! | I71: 1
A72: 001 | B72: 000124 | C72: =IFERROR(VLOOKUP(B72,'SB1'!$A$2:$B$999999,2,FALSE),"") -> AEROSOL RUST-OLEUM IMPRIMANTE PLASTICO PRIMER GRIS X 0,340 (252472/371258) | D72: 0902 | E72: =IFERROR(VLOOKUP(B72,'DA1'!$B$2:$D$999999,3,FALSE),"") | F72: =IFERROR(VLOOKUP(B72,'SB1'!$A$2:$C$999999,3,FALSE),"") -> 503 | G72: =E72*1.04 -> #VALUE! | H72: =G72*1.21 -> #VALUE!
A73: 001 | B73: 000128 | C73: =IFERROR(VLOOKUP(B73,'SB1'!$A$2:$B$999999,2,FALSE),"") -> LACA PARA PISO PETRILAC PLASTILAC X 1 | D73: 0138 | E73: =IFERROR(VLOOKUP(B73,'DA1'!$B$2:$D$999999,3,FALSE),"") | F73: =IFERROR(VLOOKUP(B73,'SB1'!$A$2:$C$999999,3,FALSE),"") -> 503 | G73: =E73*1.04 -> #VALUE! | H73: =G73*1.21 -> #VALUE! | I73: 1
A74: 001 | B74: 000129 | C74: =IFERROR(VLOOKUP(B74,'SB1'!$A$2:$B$999999,2,FALSE),"") -> LACA PARA PISO PETRILAC PLASTILAC X 4 | D74: 0138 | E74: =IFERROR(VLOOKUP(B74,'DA1'!$B$2:$D$999999,3,FALSE),"") | F74: =IFERROR(VLOOKUP(B74,'SB1'!$A$2:$C$999999,3,FALSE),"") -> 503 | G74: =E74*1.04 -> #VALUE! | H74: =G74*1.21 -> #VALUE! | I74: 1
A75: 001 | B75: 000130 | C75: =IFERROR(VLOOKUP(B75,'SB1'!$A$2:$B$999999,2,FALSE),"") -> ESMALTE SINTETICO TERSUAVE 2EN1 MATE BLANCO X 0,250 | D75: 0152 | E75: =IFERROR(VLOOKUP(B75,'DA1'!$B$2:$D$999999,3,FALSE),"") | F75: =IFERROR(VLOOKUP(B75,'SB1'!$A$2:$C$999999,3,FALSE),"") -> 503 | G75: =E75*1.04 -> #VALUE! | H75: =G75*1.21 -> #VALUE! | I75: 1
A76: 001 | B76: 000131 | C76: =IFERROR(VLOOKUP(B76,'SB1'!$A$2:$B$999999,2,FALSE),"") -> ESMALTE SINTETICO TERSUAVE 2EN1 MATE BLANCO X 20 | D76: 0152 | E76: =IFERROR(VLOOKUP(B76,'DA1'!$B$2:$D$999999,3,FALSE),"") | F76: =IFERROR(VLOOKUP(B76,'SB1'!$A$2:$C$999999,3,FALSE),"") -> 503 | G76: =E76*1.04 -> #VALUE! | H76: =G76*1.21 -> #VALUE! | I76: 1
A77: 001 | B77: 000132 | C77: =IFERROR(VLOOKUP(B77,'SB1'!$A$2:$B$999999,2,FALSE),"") -> LATEX PARA CIELORRASOS ALBA MATE BLANCO X 10 | D77: 0107 | E77: =IFERROR(VLOOKUP(B77,'DA1'!$B$2:$D$999999,3,FALSE),"") | F77: =IFERROR(VLOOKUP(B77,'SB1'!$A$2:$C$999999,3,FALSE),"") -> 503 | G77: =E77*1.04 -> #VALUE! | H77: =G77*1.21 -> #VALUE! | I77: 1
A78: 001 | B78: 000133 | C78: =IFERROR(VLOOKUP(B78,'SB1'!$A$2:$B$999999,2,FALSE),"") -> ENTONADOR UNIVERSAL TONALBA 001 AMARILLO X 0,030 | D78: 0107 | E78: =IFERROR(VLOOKUP(B78,'DA1'!$B$2:$D$999999,3,FALSE),"") | F78: =IFERROR(VLOOKUP(B78,'SB1'!$A$2:$C$999999,3,FALSE),"") -> 503 | G78: =E78*1.04 -> #VALUE! | H78: =G78*1.21 -> #VALUE! | I78: 1
A79: 001 | B79: 000134 | C79: =IFERROR(VLOOKUP(B79,'SB1'!$A$2:$B$999999,2,FALSE),"") -> ENTONADOR UNIVERSAL TONALBA 002 BERMELLON X 0,030 | D79: 0107 | E79: =IFERROR(VLOOKUP(B79,'DA1'!$B$2:$D$999999,3,FALSE),"") | F79: =IFERROR(VLOOKUP(B79,'SB1'!$A$2:$C$999999,3,FALSE),"") -> 503 | G79: =E79*1.04 -> #VALUE! | H79: =G79*1.21 -> #VALUE! | I79: 1
A80: 001 | B80: 000135 | C80: =IFERROR(VLOOKUP(B80,'SB1'!$A$2:$B$999999,2,FALSE),"") -> ENTONADOR UNIVERSAL TONALBA 003 OCRE X 0,030 | D80: 0107 | E80: =IFERROR(VLOOKUP(B80,'DA1'!$B$2:$D$999999,3,FALSE),"") | F80: =IFERROR(VLOOKUP(B80,'SB1'!$A$2:$C$999999,3,FALSE),"") -> 503 | G80: =E80*1.04 -> #VALUE! | H80: =G80*1.21 -> #VALUE! | I80: 1
A81: 001 | B81: 000136 | C81: =IFERROR(VLOOKUP(B81,'SB1'!$A$2:$B$999999,2,FALSE),"") -> ENTONADOR UNIVERSAL TONALBA 004 VERDE CLARO X 0,030 | D81: 0107 | E81: =IFERROR(VLOOKUP(B81,'DA1'!$B$2:$D$999999,3,FALSE),"") | F81: =IFERROR(VLOOKUP(B81,'SB1'!$A$2:$C$999999,3,FALSE),"") -> 503 | G81: =E81*1.04 -> #VALUE! | H81: =G81*1.21 -> #VALUE! | I81: 1
A82: 001 | B82: 000137 | C82: =IFERROR(VLOOKUP(B82,'SB1'!$A$2:$B$999999,2,FALSE),"") -> ENTONADOR UNIVERSAL TONALBA 005 VERDE OSCURO X 0,030 | D82: 0107 | E82: =IFERROR(VLOOKUP(B82,'DA1'!$B$2:$D$999999,3,FALSE),"") | F82: =IFERROR(VLOOKUP(B82,'SB1'!$A$2:$C$999999,3,FALSE),"") -> 503 | G82: =E82*1.04 -> #VALUE! | H82: =G82*1.21 -> #VALUE! | I82: 1
A83: 001 | B83: 000138 | C83: =IFERROR(VLOOKUP(B83,'SB1'!$A$2:$B$999999,2,FALSE),"") -> ENTONADOR UNIVERSAL TONALBA 006 AZUL X 0,030 | D83: 0107 | E83: =IFERROR(VLOOKUP(B83,'DA1'!$B$2:$D$999999,3,FALSE),"") | F83: =IFERROR(VLOOKUP(B83,'SB1'!$A$2:$C$999999,3,FALSE),"") -> 503 | G83: =E83*1.04 -> #VALUE! | H83: =G83*1.21 -> #VALUE! | I83: 1
A84: 001 | B84: 000139 | C84: =IFERROR(VLOOKUP(B84,'SB1'!$A$2:$B$999999,2,FALSE),"") -> ENTONADOR UNIVERSAL TONALBA 007 CEDRO X 0,030 | D84: 0107 | E84: =IFERROR(VLOOKUP(B84,'DA1'!$B$2:$D$999999,3,FALSE),"") | F84: =IFERROR(VLOOKUP(B84,'SB1'!$A$2:$C$999999,3,FALSE),"") -> 503 | G84: =E84*1.04 -> #VALUE! | H84: =G84*1.21 -> #VALUE! | I84: 1
... A124: 001 | B124: 000185 | C124: =IFERROR(VLOOKUP(B124,'SB1'!$A$2:$B$999999,2,FALSE),"") -> AEROSOL RUST-OLEUM PARA PLASTICO BRILLANTE NEGRO X 0,340 (248649) | D124: 0145 | E124: =IFERROR(VLOOKUP(B124,'DA1'!$B$2:$D$999999,3,FALSE),"") | F124: =IFERROR(VLOOKUP(B124,'SB1'!$A$2:$C$999999,3,FALSE),"") -> 503 | G124: =E124*1.04 -> #VALUE! | H124: =G124*1.21 -> #VALUE! | I124: 1
A125: 001 | B125: 000189 | C125: =IFERROR(VLOOKUP(B125,'SB1'!$A$2:$B$999999,2,FALSE),"") -> AEROSOL RUST-OLEUM PARA PLASTICO BRILLANTE ROJO X 0,340 (248651) | D125: 0902 | E125: =IFERROR(VLOOKUP(B125,'DA1'!$B$2:$D$999999,3,FALSE),"") | F125: =IFERROR(VLOOKUP(B125,'SB1'!$A$2:$C$999999,3,FALSE),"") -> 503 | G125: =E125*1.04 -> #VALUE! | H125: =G125*1.21 -> #VALUE!
A126: 001 | B126: 000193 | C126: =IFERROR(VLOOKUP(B126,'SB1'!$A$2:$B$999999,2,FALSE),"") -> FONDO PARA MADERA ALBA BLANCO X 20 | D126: 0107 | E126: =IFERROR(VLOOKUP(B126,'DA1'!$B$2:$D$999999,3,FALSE),"") | F126: =IFERROR(VLOOKUP(B126,'SB1'!$A$2:$C$999999,3,FALSE),"") -> 503 | G126: =E126*1.04 -> #VALUE! | H126: =G126*1.21 -> #VALUE! | I126: 1
A127: 001 | B127: 000194 | C127: =IFERROR(VLOOKUP(B127,'SB1'!$A$2:$B$999999,2,FALSE),"") -> FRATACHO DE PINO 30CM CON FIELTRO (FR16) | D127: 0176 | E127: =IFERROR(VLOOKUP(B127,'DA1'!$B$2:$D$999999,3,FALSE),"") | F127: =IFERROR(VLOOKUP(B127,'SB1'!$A$2:$C$999999,3,FALSE),"") -> 503 | G127: =E127*1.04 -> #VALUE! | H127: =G127*1.21 -> #VALUE! | I127: 1
A128: 001 | B128: 000195 | C128: =IFERROR(VLOOKUP(B128,'SB1'!$A$2:$B$999999,2,FALSE),"") -> FONDO ANTIOXIDO ALBA ROJO X 0,500 | D128: 0107 | E128: =IFERROR(VLOOKUP(B128,'DA1'!$B$2:$D$999999,3,FALSE),"") | F128: =IFERROR(VLOOKUP(B128,'SB1'!$A$2:$C$999999,3,FALSE),"") -> 503 | G128: =E128*1.04 -> #VALUE! | H128: =G128*1.21 -> #VALUE! | I128: 1
A129: 001 | B129: 000196 | C129: =IFERROR(VLOOKUP(B129,'SB1'!$A$2:$B$999999,2,FALSE),"") -> FONDO ANTIOXIDO ALBA ROJO X 1 | D129: 0902 | E129: =IFERROR(VLOOKUP(B129,'DA1'!$B$2:$D$999999,3,FALSE),"") | F129: =IFERROR(VLOOKUP(B129,'SB1'!$A$2:$C$999999,3,FALSE),"") -> 503 | G129: =E129*1.04 -> #VALUE! | H129: =G129*1.21 -> #VALUE! | I129: 1
A130: 001 | B130: 000197 | C130: =IFERROR(VLOOKUP(B130,'SB1'!$A$2:$B$999999,2,FALSE),"") -> FONDO ANTIOXIDO ALBA ROJO X 4 | D130: 0902 | E130: =IFERROR(VLOOKUP(B130,'DA1'!$B$2:$D$999999,3,FALSE),"") | F130: =IFERROR(VLOOKUP(B130,'SB1'!$A$2:$C$999999,3,FALSE),"") -> 503 | G130: =E130*1.04 -> #VALUE! | H130: =G130*1.21 -> #VALUE! | I130: 1
A131: 001 | B131: 000198 | C131: =IFERROR(VLOOKUP(B131,'SB1'!$A$2:$B$999999,2,FALSE),"") -> FONDO ANTIOXIDO ALBA ROJO X 20 | D131: 0107 | E131: =IFERROR(VLOOKUP(B131,'DA1'!$B$2:$D$999999,3,FALSE),"") | F131: =IFERROR(VLOOKUP(B131,'SB1'!$A$2:$C$999999,3,FALSE),"") -> 503 | G131: =E131*1.04 -> #VALUE! | H131: =G131*1.21 -> #VALUE! | I131: 1
A132: 001 | B132: 000199 | C132: =IFERROR(VLOOKUP(B132,'SB1'!$A$2:$B$999999,2,FALSE),"") -> FONDO PARA MADERA ALBA BLANCO X 0,500 | D132: 0107 | E132: =IFERROR(VLOOKUP(B132,'DA1'!$B$2:$D$999999,3,FALSE),"") | F132: =IFERROR(VLOOKUP(B132,'SB1'!$A$2:$C$999999,3,FALSE),"") -> 503 | G132: =E132*1.04 -> #VALUE! | H132: =G132*1.21 -> #VALUE! | I132: 1
A133: 001 | B133: 000200 | C133: =IFERROR(VLOOKUP(B133,'SB1'!$A$2:$B$999999,2,FALSE),"") -> FONDO PARA MADERA ALBA BLANCO X 1 | D133: 0107 | E133: =IFERROR(VLOOKUP(B133,'DA1'!$B$2:$D$999999,3,FALSE),"") | F133: =IFERROR(VLOOKUP(B133,'SB1'!$A$2:$C$999999,3,FALSE),"") -> 503 | G133: =E133*1.04 -> #VALUE! | H133: =G133*1.21 -> #VALUE! | I133: 1
A134: 001 | B134: 000201 | C134: =IFERROR(VLOOKUP(B134,'SB1'!$A$2:$B$999999,2,FALSE),"") -> FONDO PARA MADERA ALBA BLANCO X 4 | D134: 0107 | E134: =IFERROR(VLOOKUP(B134,'DA1'!$B$2:$D$999999,3,FALSE),"") | F134: =IFERROR(VLOOKUP(B134,'SB1'!$A$2:$C$999999,3,FALSE),"") -> 503 | G134: =E134*1.04 -> #VALUE! | H134: =G134*1.21 -> #VALUE! | I134: 1
A135: 001 | B135: 000203 | C135: =IFERROR(VLOOKUP(B135,'SB1'!$A$2:$B$999999,2,FALSE),"") -> BARNIZ PARA MADERA EXTERIOR ALBATROS BRILLANTE DOBLE VIDA INCOLORO X 0,500 | D135: 0902 | E135: =IFERROR(VLOOKUP(B135,'DA1'!$B$2:$D$999999,3,FALSE),"") | F135: =IFERROR(VLOOKUP(B135,'SB1'!$A$2:$C$999999,3,FALSE),"") -> 503 | G135: =E135*1.04 -> #VALUE! | H135: =G135*1.21 -> #VALUE!
A136: 001 | B136: 000204 | C136: =IFERROR(VLOOKUP(B136,'SB1'!$A$2:$B$999999,2,FALSE),"") -> BARNIZ PARA MADERA EXTERIOR ALBATROS BRILLANTE NATURAL X 1 | D136: 0107 | E136: =IFERROR(VLOOKUP(B136,'DA1'!$B$2:$D$999999,3,FALSE),"") | F136: =IFERROR(VLOOKUP(B136,'SB1'!$A$2:$C$999999,3,FALSE),"") -> 503 | G136: =E136*1.04 -> #VALUE! | H136: =G136*1.21 -> #VALUE! | I136: 1
A137: 001 | B137: 000205 | C137: =IFERROR(VLOOKUP(B137,'SB1'!$A$2:$B$999999,2,FALSE),"") -> BARNIZ PARA MADERA EXTERIOR ALBATROS BRILLANTE NATURAL X 4 | D137: 0107 | E137: =IFERROR(VLOOKUP(B137,'DA1'!$B$2:$D$999999,3,FALSE),"") | F137: =IFERROR(VLOOKUP(B137,'SB1'!$A$2:$C$999999,3,FALSE),"") -> 503 | G137: =E137*1.04 -> #VALUE! | H137: =G137*1.21 -> #VALUE! | I137: 1
A138: 001 | B138: 000208 | C138: =IFERROR(VLOOKUP(B138,'SB1'!$A$2:$B$999999,2,FALSE),"") -> BARNIZ PARA MADERA INTERIOR CRISTALBA PU BRILLANTE NATURAL X 1 | D138: 0107 | E138: =IFERROR(VLOOKUP(B138,'DA1'!$B$2:$D$999999,3,FALSE),"") | F138: =IFERROR(VLOOKUP(B138,'SB1'!$A$2:$C$999999,3,FALSE),"") -> 503 | G138: =E138*1.04 -> #VALUE! | H138: =G138*1.21 -> #VALUE! | I138: 1
A139: 001 | B139: 000209 | C139: =IFERROR(VLOOKUP(B139,'SB1'!$A$2:$B$999999,2,FALSE),"") -> BARNIZ PARA MADERA INTERIOR CRISTALBA PU BRILLANTE NATURAL X 4 | D139: 0107 | E139: =IFERROR(VLOOKUP(B139,'DA1'!$B$2:$D$999999,3,FALSE),"") | F139: =IFERROR(VLOOKUP(B139,'SB1'!$A$2:$C$999999,3,FALSE),"") -> 503 | G139: =E139*1.04 -> #VALUE! | H139: =G139*1.21 -> #VALUE! | I139: 1
A140: 001 | B140: 000211 | C140: =IFERROR(VLOOKUP(B140,'SB1'!$A$2:$B$999999,2,FALSE),"") -> DISCO REMOVEDOR DE ADHESIVO 89X | D140: 0102 | E140: =IFERROR(VLOOKUP(B140,'DA1'!$B$2:$D$999999,3,FALSE),"") | F140: =IFERROR(VLOOKUP(B140,'SB1'!$A$2:$C$999999,3,FALSE),"") -> 503 | G140: =E140*1.04 -> #VALUE! | H140: =G140*1.21 -> #VALUE! | I140: 1
A141: 001 | B141: 000216 | C141: =IFERROR(VLOOKUP(B141,'SB1'!$A$2:$B$999999,2,FALSE),"") -> AGITADOR MANUAL PARA PINTURAS | D141: 0103 | E141: =IFERROR(VLOOKUP(B141,'DA1'!$B$2:$D$999999,3,FALSE),"") | F141: =IFERROR(VLOOKUP(B141,'SB1'!$A$2:$C$999999,3,FALSE),"") -> 503 | G141: =E141*1.04 -> #VALUE! | H141: =G141*1.21 -> #VALUE! | I141: 1
A142: 001 | B142: 000217 | C142: =IFERROR(VLOOKUP(B142,'SB1'!$A$2:$B$999999,2,FALSE),"") -> COLA PAPEL COLVINIL X 0,250 | D142: 0119 | E142: =IFERROR(VLOOKUP(B142,'DA1'!$B$2:$D$999999,3,FALSE),"") | F142: =IFERROR(VLOOKUP(B142,'SB1'!$A$2:$C$999999,3,FALSE),"") -> 503 | G142: =E142*1.04 -> #VALUE! | H142: =G142*1.21 -> #VALUE! | I142: 1
A143: 001 | B143: 000218 | C143: =IFERROR(VLOOKUP(B143,'SB1'!$A$2:$B$999999,2,FALSE),"") -> PM01.04 PRIMER MULTIFILLER 1K ACS X 0.900 | D143: 0132 | E143: =IFERROR(VLOOKUP(B143,'DA1'!$B$2:$D$999999,3,FALSE),"") | F143: =IFERROR(VLOOKUP(B143,'SB1'!$A$2:$C$999999,3,FALSE),"") -> 503 | G143: =E143*1.04 -> #VALUE! | H143: =G143*1.21 -> #VALUE! | I143: 3
A144: 001 | B144: 000219 | C144: =IFERROR(VLOOKUP(B144,'SB1'!$A$2:$B$999999,2,FALSE),"") -> COLA PAPEL COLVINIL X 0,500 | D144: 0119 | E144: =IFERROR(VLOOKUP(B144,'DA1'!$B$2:$D$999999,3,FALSE),"") | F144: =IFERROR(VLOOKUP(B144,'SB1'!$A$2:$C$999999,3,FALSE),"") -> 503 | G144: =E144*1.04 -> #VALUE! | H144: =G144*1.21 -> #VALUE! | I144: 1
A145: 001 | B145: 000220 | C145: =IFERROR(VLOOKUP(B145,'SB1'!$A$2:$B$999999,2,FALSE),"") -> FBR551 CLEAR EPOXI MAXIPISO X 20 | D145: 0133 | E145: =IFERROR(VLOOKUP(B145,'DA1'!$B$2:$D$999999,3,FALSE),"") | F145: =IFERROR(VLOOKUP(B145,'SB1'!$A$2:$C$999999,3,FALSE),"") -> 503 | G145: =E145*1.04 -> #VALUE! | H145: =G145*1.21 -> #VALUE! | I145: 3
A146: 001 | B146: 000221 | C146: =IFERROR(VLOOKUP(B146,'SB1'!$A$2:$B$999999,2,FALSE),"") -> FBR560 ENDURECEDOR EPOXI MAXIPISO X 0,600 | D146: 0133 | E146: =IFERROR(VLOOKUP(B146,'DA1'!$B$2:$D$999999,3,FALSE),"") | F146: =IFERROR(VLOOKUP(B146,'SB1'!$A$2:$C$999999,3,FALSE),"") -> 503 | G146: =E146*1.04 -> #VALUE! | H146: =G146*1.21 -> #VALUE! | I146: 3
A147: 001 | B147: 000222 | C147: =IFERROR(VLOOKUP(B147,'SB1'!$A$2:$B$999999,2,FALSE),"") -> FBR100 PRIMER PU DIRECTO METAL X 20 | D147: 0133 | E147: =IFERROR(VLOOKUP(B147,'DA1'!$B$2:$D$999999,3,FALSE),"") | F147: =IFERROR(VLOOKUP(B147,'SB1'!$A$2:$C$999999,3,FALSE),"") -> 503 | G147: =E147*1.04 -> #VALUE! | H147: =G147*1.21 -> #VALUE! | I147: 3
...

Sheet DA1
A1: Cod. Tabla | B1: Cod.Producto | C1: Grupo | D1: Precio Venta | E1: Moneda
A2: 1 | B2: 2 | C2: 165 | D2: 7361.28 | E2: 1
A3: 1 | B3: 3 | C3: 165 | D3: 8634.19 | E3: 1
A4: 1 | B4: 4 | C4: 165 | D4: 5167.87 | E4: 1
A5: 1 | B5: 5 | C5: 902 | D5: 1150.05 | E5: 1
A6: 1 | B6: 6 | C6: 165 | D6: 5150.97 | E6: 1
A7: 1 | B7: 7 | C7: 165 | D7: 6906.78 | E7: 1
A8: 1 | B8: 8 | C8: 165 | D8: 8930.2 | E8: 1
A9: 1 | B9: 10 | C9: 152 | D9: 10082.07 | E9: 1
A10: 1 | B10: 11 | C10: 152 | D10: 15006.36 | E10: 1
A11: 1 | B11: 12 | C11: 152 | D11: 52809.36 | E11: 1
A12: 1 | B12: 13 | C12: 152 | D12: 11883.21 | E12: 1
A13: 1 | B13: 14 | C13: 152 | D13: 18043.58 | E13: 1
... A4629: 1 | B4629: 200623 | C4629: 120 | D4629: 219056.08 | E4629: 1

Sheet ListaCorte
A1: Cod.Producto | B1: Descripcion | C1: Grupo | D1: Final | E1: Moneda
A2: ='001'!B2 -> 000002 | B2: ='001'!C2 -> CINTA PELIGRO X 100 MTS DOBLE FAZ(CP100) | C2: ='001'!D2 -> 0165 | D2: ='001'!H2 -> #VALUE!
A3: ='001'!B3 -> 000003 | B3: ='001'!C3 -> CINTA PELIGRO X 200 MTS DOBLE FAZ(CP200) | C3: ='001'!D3 -> 0165 | D3: ='001'!H3 -> #VALUE!
A4: ='001'!B4 -> 000004 | B4: ='001'!C4 -> PISTOLA APLICADORA SKELETOR REFORZADA | C4: ='001'!D4 -> 0165 | D4: ='001'!H4 -> #VALUE!
A5: ='001'!B5 -> 000005 | B5: ='001'!C5 -> PORTA PINCEL MAGNETICO | C5: ='001'!D5 -> 0165 | D5: ='001'!H5 -> #VALUE!
A6: ='001'!B6 -> 000006 | B6: ='001'!C6 -> COBERTURA PLASTICA MULTIUSO 3X3MTS.(AC315) | C6: ='001'!D6 -> 0165 | D6: ='001'!H6 -> #VALUE!
A7: ='001'!B7 -> 000007 | B7: ='001'!C7 -> COBERTURA PLASTICA MULTIUSO 3X4MTS.(AC316) | C7: ='001'!D7 -> 0165 | D7: ='001'!H7 -> #VALUE!
A8: ='001'!B8 -> 000008 | B8: ='001'!C8 -> COBERTURA PLASTICA MULTIUSO 3X5MTS.(AC317) | C8: ='001'!D8 -> 0165 | D8: ='001'!H8 -> #VALUE!
A9: ='001'!B9 -> 000010 | B9: ='001'!C9 -> ESMALTE SINTETICO TERSUAVE 2EN1 MATE NEGRO X 0,500 | C9: ='001'!D9 -> 0152 | D9: ='001'!H9 -> #VALUE!
A10: ='001'!B10 -> 000011 | B10: ='001'!C10 -> ESMALTE SINTETICO TERSUAVE 2EN1 MATE NEGRO X 1 | C10: ='001'!D10 -> 0152 | D10: ='001'!H10 -> #VALUE!
A11: ='001'!B11 -> 000012 | B11: ='001'!C11 -> ESMALTE SINTETICO TERSUAVE 2EN1 MATE NEGRO X 4 | C11: ='001'!D11 -> 0152 | D11: ='001'!H11 -> #VALUE!
A12: ='001'!B12 -> 000013 | B12: ='001'!C12 -> ESMALTE SINTETICO TERSUAVE 2EN1 MATE BLANCO X 0,500 | C12: ='001'!D12 -> 0152 | D12: ='001'!H12 -> #VALUE!
A13: ='001'!B13 -> 000014 | B13: ='001'!C13 -> ESMALTE SINTETICO TERSUAVE 2EN1 MATE BLANCO X 1 | C13: ='001'!D13 -> 0152 | D13: ='001'!H13 -> #VALUE!
... A4628: ='001'!B4628 -> 200623 | B4628: ='001'!C4628 -> DILUYENTE SECADO A AIRE DIXILINA NRO.3 X 200 | C4628: ='001'!D4628 -> 0120 | D4628: ='001'!H4628 -> #VALUE!
